ATS_Library-1.2.data/data/LICENSE
ats/__init__.py
ats/api_test/__init__.py
ats/api_test/http_common.py
ats/api_test/websocket_common.py
ats/app_test/__init__.py
ats/common/__init__.py
ats/common/assertion/__init__.py
ats/common/assertion/assert_common.py
ats/common/assertion/soft_assert_common.py
ats/common/config/__init__.py
ats/common/config/conf_common.py
ats/common/csv/__init__.py
ats/common/csv/csv_common.py
ats/common/database/__init__.py
ats/common/database/sqlalchemy_common.py
ats/common/json/__init__.py
ats/common/json/json_common.py
ats/common/log/__init__.py
ats/common/log/config.py
ats/common/log/log.py
ats/common/ocr/__init__.py
ats/common/ocr/ocr_common.py
ats/common/re/__init__.py
ats/common/re/re_common.py
ats/common/time/__init__.py
ats/common/time/time_common.py
ats/common/tree/__init__.py
ats/common/tree/tree_common.py
ats/common/yaml/__init__.py
ats/common/yaml/yaml_common.py
ats/constant/__init__.py
ats/constant/color_const.py
ats/constant/date_format.py
ats/performance_test/__init__.py
ats/security_test/__init__.py
ats/unit_test/__init__.py
ats/web_test/__init__.py
ats/web_test/selenium/__init__.py
ats/web_test/selenium/basepage.py
ats/web_test/selenium/action_word/__init__.py
ats/web_test/selenium/action_word/aw_common.py
ats/web_test/selenium/browser/__init__.py
ats/web_test/selenium/browser/browser_common.py
ats/web_test/selenium/selenium_common/__init__.py
ats/web_test/selenium/selenium_common/alert.py
ats/web_test/selenium/selenium_common/driver.py
ats/web_test/selenium/selenium_common/ec.py
ats/web_test/selenium/selenium_common/element.py
ats/web_test/selenium/selenium_common/keyboard.py
ats/web_test/selenium/selenium_common/mouse.py
ats/web_test/selenium/selenium_common/select.py
ats/web_test/selenium/selenium_common/ui.py
ats/web_test/selenium/selenium_common/wait.py
ATS_Library-1.2.dist-info/LICENSE
ATS_Library-1.2.dist-info/METADATA
ATS_Library-1.2.dist-info/WHEEL
ATS_Library-1.2.dist-info/top_level.txt
ATS_Library-1.2.dist-info/RECORD
