Metadata-Version: 2.1
Name: ATS-Library
Version: 1.2
Summary: Auto Test Suite Library
Home-page: https://github.com/isguxin/ATS-Library
Author: Gu Xin
Author-email: g_xin@outlook.com
Maintainer: Gu Xin
Maintainer-email: g_xin@outlook.com
License: MIT
Keywords: auto test suite library
Platform: Windows
Platform: Linux
Platform: Unix
Platform: Mac OS-X
Classifier: Development Status :: 1 - Planning
Classifier: Intended Audience :: Developers
Classifier: License :: OSI Approved :: MIT License
Classifier: Operating System :: OS Independent
Classifier: Programming Language :: Python :: 3
Classifier: Programming Language :: Python :: 3.8
Classifier: Programming Language :: Python :: 3.9
Classifier: Programming Language :: Python :: 3.10
Classifier: Topic :: Software Development :: Testing
Classifier: Topic :: Software Development :: Libraries :: Python Modules
Requires-Python: <3.11
License-File: LICENSE
Requires-Dist: requests
Requires-Dist: websocket-client
Requires-Dist: colorlog
Requires-Dist: sqlalchemy
Requires-Dist: treelib
Requires-Dist: PyYAML
Requires-Dist: easy-ocr
Requires-Dist: ddddocr
Requires-Dist: selenium
Requires-Dist: pytest
Requires-Dist: pytest-html
Requires-Dist: pytest-rerunfailures
Requires-Dist: pytest-xdist
Requires-Dist: pytest-ordering
Requires-Dist: allure-pytest
